pandas_chat/__init__.py
pandas_chat/action.py
pandas_chat/factory.py
pandas_chat/utils.py
pandas_chat-0.0.3.dist-info/LICENSE
pandas_chat-0.0.3.dist-info/METADATA
pandas_chat-0.0.3.dist-info/WHEEL
pandas_chat-0.0.3.dist-info/top_level.txt
pandas_chat-0.0.3.dist-info/RECORD
