Metadata-Version: 2.1
Name: pandas-chat
Version: 0.0.3
Summary: pandas-ai is a python library that uses ChatGPT prompts         to analyze and process pandas data in a conversational way.
Home-page: https://github.com/torshind/pandas-ai
Author: torshind
License: BSD 3-Clause
Keywords: pandas,chatgpt
License-File: LICENSE
Requires-Dist: openai
Requires-Dist: hugchat
